Metadata-Version: 2.4
Name: contextvault
Version: 0.2.1
Summary: Local-first context archival system with PNG serialization and AI indexing
Home-page: https://github.com/saisurya76/contextvault
Author: Suryanarayana Bollapragada
Author-email: Suryanarayana Bollapragada <you@example.com>
License: MIT
Requires-Python: >=3.9
Requires-Dist: fastapi<1.0.0,>=0.111.0
Requires-Dist: uvicorn[standard]<1.0.0,>=0.30.0
Requires-Dist: pillow<11.0.0,>=10.3.0
Requires-Dist: numpy==1.26.4
Requires-Dist: python-multipart<0.1.0,>=0.0.9
Requires-Dist: python-jose[cryptography]==3.3.0
Requires-Dist: passlib[bcrypt]==1.7.4
Requires-Dist: bcrypt==4.0.1
Requires-Dist: python-dotenv==1.0.0
Requires-Dist: cryptography==41.0.4
Requires-Dist: httpx<1.0.0,>=0.27.0
Requires-Dist: requests<3.0.0,>=2.32.0
Requires-Dist: jsonschema>=4.25.1
Provides-Extra: dev
Requires-Dist: pytest<9.0.0,>=8.0.0; extra == "dev"
Requires-Dist: pytest-asyncio<0.24.0,>=0.23.0; extra == "dev"
Requires-Dist: black<25.0.0,>=24.0.0; extra == "dev"
Requires-Dist: isort<6.0.0,>=5.13.0; extra == "dev"
Requires-Dist: httpx<1.0.0,>=0.27.0; extra == "dev"
Requires-Dist: requests<3.0.0,>=2.32.0; extra == "dev"
